akerbp/models/__init__.py
akerbp/models/classification_models/__init__.py
akerbp/models/classification_models/hierarchical_model.py
akerbp/models/classification_models/nested_models.py
akerbp/models/regression_models/__init__.py
akerbp/models/rule_based_models/BS_helpers.py
akerbp/models/rule_based_models/__init__.py
akerbp/models/rule_based_models/casing_helpers.py
akerbp/models/rule_based_models/correlate_helpers.py
akerbp/models/rule_based_models/crossplot_helpers.py
akerbp/models/rule_based_models/dencorr_helpers.py
akerbp/models/rule_based_models/flatline_helpers.py
akerbp/models/rule_based_models/flatline_helpers_old.py
akerbp/models/rule_based_models/helpers.py
akerbp/models/rule_based_models/logtrend_helpers.py
akerbp/models/rule_based_models/outliers_helpers.py
akerbp/models/rule_based_models/resistivities_helpers.py
akerbp/models/rule_based_models/umap_helpers.py
akerbp/models/rule_based_models/washout_helpers.py
akerbp.models-1.20220304142108.dist-info/LICENSE
akerbp.models-1.20220304142108.dist-info/METADATA
akerbp.models-1.20220304142108.dist-info/WHEEL
akerbp.models-1.20220304142108.dist-info/top_level.txt
akerbp.models-1.20220304142108.dist-info/RECORD
