Metadata-Version: 2.1
Name: akerbp.models
Version: 1.20220304142108
Summary: Machine Learning Models for Petrophysics
Home-page: https://bitbucket.org/akerbp/models/
Author: Alfonso M. Canterla
Author-email: alfonso.canterla@soprasteria.com
License: UNKNOWN
Platform: UNKNOWN
Classifier: Programming Language :: Python :: 3
Classifier: License :: OSI Approved :: MIT License
Classifier: Operating System :: OS Independent
Requires-Python: >=3.8
License-File: LICENSE
Requires-Dist: xgboost (==1.3.3)
Requires-Dist: joblib (==1.0.1)
Requires-Dist: numpy (>=1.19.5)
Requires-Dist: pandas (>=1.3.2)
Requires-Dist: scikit-learn (>=0.24.2)
